stickleback/__init__.py
stickleback/data.py
stickleback/stickleback.py
stickleback/types.py
stickleback/util.py
stickleback/visualize.py
stickleback/data/events.csv
stickleback/data/sensors.csv
stickleback-0.1.6.dist-info/METADATA
stickleback-0.1.6.dist-info/WHEEL
stickleback-0.1.6.dist-info/top_level.txt
stickleback-0.1.6.dist-info/RECORD
