Metadata-Version: 2.1
Name: stickleback
Version: 0.1.6
Summary: Automated behavioral event detection in bio-logging data.
Home-page: http://github.com/FlukeAndFeather/stickleback
Author: Max Czapanskiy
Author-email: maxczapanskiy@gmail.com
License: MIT
Requires-Dist: jupyter
Requires-Dist: matplotlib
Requires-Dist: numpy (<1.22,>=1.21.0)
Requires-Dist: pandas
Requires-Dist: plotly
Requires-Dist: scikit-learn
Requires-Dist: scipy
Requires-Dist: sktime (>=0.11)
